CHANGES.rst
CONTRIBUTORS.rst
DEVELOP.rst
LICENSE.rst
MANIFEST.in
README.rst
setup.cfg
setup.py
docs/index.rst
src/rg/__init__.py
src/rg.prenotazioni.egg-info/PKG-INFO
src/rg.prenotazioni.egg-info/SOURCES.txt
src/rg.prenotazioni.egg-info/dependency_links.txt
src/rg.prenotazioni.egg-info/entry_points.txt
src/rg.prenotazioni.egg-info/namespace_packages.txt
src/rg.prenotazioni.egg-info/not-zip-safe
src/rg.prenotazioni.egg-info/requires.txt
src/rg.prenotazioni.egg-info/top_level.txt
src/rg/prenotazioni/__init__.py
src/rg/prenotazioni/config.py
src/rg/prenotazioni/configure.zcml
src/rg/prenotazioni/event.py
src/rg/prenotazioni/indexes.py
src/rg/prenotazioni/interfaces.py
src/rg/prenotazioni/permissions.zcml
src/rg/prenotazioni/prenotazione_event.py
src/rg/prenotazioni/setuphandlers.py
src/rg/prenotazioni/testing.py
src/rg/prenotazioni/upgrades.py
src/rg/prenotazioni/upgrades.zcml
src/rg/prenotazioni/actions/__init__.py
src/rg/prenotazioni/actions/configure.zcml
src/rg/prenotazioni/actions/mail.py
src/rg/prenotazioni/adapters/__init__.py
src/rg/prenotazioni/adapters/booker.py
src/rg/prenotazioni/adapters/configure.zcml
src/rg/prenotazioni/adapters/conflict.py
src/rg/prenotazioni/adapters/prenotazione_menu.py
src/rg/prenotazioni/adapters/slot.py
src/rg/prenotazioni/browser/__init__.py
src/rg/prenotazioni/browser/add_edit_view.py
src/rg/prenotazioni/browser/base.py
src/rg/prenotazioni/browser/configure.zcml
src/rg/prenotazioni/browser/custom_radio_input.pt
src/rg/prenotazioni/browser/folderfactories.py
src/rg/prenotazioni/browser/interfaces.py
src/rg/prenotazioni/browser/prenotazione.py
src/rg/prenotazioni/browser/prenotazione_add.py
src/rg/prenotazioni/browser/prenotazione_move.py
src/rg/prenotazioni/browser/prenotazione_print.py
src/rg/prenotazioni/browser/prenotazioni_context_state.py
src/rg/prenotazioni/browser/prenotazioni_portal_state.py
src/rg/prenotazioni/browser/prenotazioni_search.py
src/rg/prenotazioni/browser/vacations.py
src/rg/prenotazioni/browser/week.py
src/rg/prenotazioni/browser/z3c_custom_widget.py
src/rg/prenotazioni/browser/overrides/.gitkeep
src/rg/prenotazioni/browser/static/.gitkeep
src/rg/prenotazioni/browser/static/calendar-add.png
src/rg/prenotazioni/browser/static/calendar-icon.png
src/rg/prenotazioni/browser/static/cross-icon.png
src/rg/prenotazioni/browser/static/rg-reservation.css
