Metadata-Version: 2.1
Name: rg.prenotazioni
Version: 4.0
Summary: RenoGalliera prenotazioni
Home-page: https://pypi.python.org/pypi/rg.prenotazioni
Author: RedTurtle
Author-email: sviluppoplone@redturtle.it
License: GPL version 2
Keywords: Python Plone
Platform: UNKNOWN
Classifier: Environment :: Web Environment
Classifier: Framework :: Plone
Classifier: Framework :: Plone :: 5.0
Classifier: Framework :: Plone :: 5.1
Classifier: Programming Language :: Python
Classifier: Programming Language :: Python :: 2.7
Classifier: Operating System :: OS Independent
Classifier: License :: OSI Approved :: GNU General Public License v2 (GPLv2)
Provides-Extra: test
